AUTHORS
Changelog
INSTALL
LICENSE
MANIFEST.in
README.rst
TODO
setup.py
docs/Makefile
docs/changelog.rst
docs/conf.py
docs/index.rst
docs/introduction.rst
docs/.build/doctrees/changelog.doctree
docs/.build/doctrees/environment.pickle
docs/.build/doctrees/index.doctree
docs/.build/doctrees/introduction.doctree
docs/.build/doctrees/reference/index.doctree
docs/.build/doctrees/reference/redish.client.doctree
docs/.build/doctrees/reference/redish.models.doctree
docs/.build/doctrees/reference/redish.serialization.doctree
docs/.build/doctrees/reference/redish.types.doctree
docs/.build/doctrees/reference/redish.utils.doctree
docs/_ext/applyxrefs.py
docs/_ext/literals_to_xrefs.py
docs/_theme/nature/theme.conf
docs/_theme/nature/static/nature.css_t
docs/_theme/nature/static/pygments.css
docs/reference/index.rst
docs/reference/redish.client.rst
docs/reference/redish.models.rst
docs/reference/redish.serialization.rst
docs/reference/redish.types.rst
docs/reference/redish.utils.rst
examples/feedentries.py
redish/.__init__.py.swp
redish/.client.py.swp
redish/.models.py.swp
redish/.serialization.py.swp
redish/__init__.py
redish/__init__.pyc
redish/client.py
redish/models.py
redish/serialization.py
redish/types.py
redish/utils.py
redish.egg-info/PKG-INFO
redish.egg-info/SOURCES.txt
redish.egg-info/dependency_links.txt
redish.egg-info/not-zip-safe
redish.egg-info/requires.txt
redish.egg-info/top_level.txt
redish/tests/__init__.py
redish/tests/config.py
redish/tests/test_client.py
redish/tests/test_types.py
redish/tests/test_utils.py