Metadata-Version: 1.0
Name: redish
Version: 0.0.1
Summary: Pythonic Redis abstraction built on top of redis-py
Home-page: http://github.com/ask/redish
Author: Ask Solem
Author-email: askh@opera.com
License: BSD
Platform: any
Classifier: Development Status :: 4 - Beta
Classifier: Operating System :: OS Independent
Classifier: Programming Language :: Python
Classifier: Intended Audience :: Developers
Classifier: Topic :: Software Development :: Libraries :: Python Modules
Classifier: License :: OSI Approved :: BSD License
Classifier: Topic :: Database
Classifier: Topic :: Database :: Front-Ends
